{
  "id": "APP_HARDWARE",
  "app": "HARDWARE_STACK",
  "config": {
    "enabled_on_boot": true,
    "telemetry_period_ms": 2500,
    "led_auto_from_scene": true,
    "mic_enabled": true,
    "mic_event_threshold_pct": 72,
    "mic_event_name": "SERIAL:MIC_SPIKE",
    "la_trigger_enabled": true,
    "la_target_hz": 440,
    "la_tolerance_hz": 10,
    "la_max_abs_cents": 42,
    "la_min_confidence": 28,
    "la_min_level_pct": 8,
    "la_stable_ms": 3000,
    "la_release_ms": 50,
    "la_cooldown_ms": 1400,
    "la_timeout_ms": 60000,
    "la_event_name": "SERIAL:BTN_NEXT",
    "battery_enabled": true,
    "battery_low_pct": 20,
    "battery_low_event_name": "SERIAL:BATTERY_LOW"
  }
}
